netbox_manage_project/__init__.py
netbox_manage_project/forms.py
netbox_manage_project/navigation.py
netbox_manage_project/tables.py
netbox_manage_project/template_content.py
netbox_manage_project/urls.py
netbox_manage_project/api/__init__.py
netbox_manage_project/api/serializers.py
netbox_manage_project/api/urls.py
netbox_manage_project/api/views.py
netbox_manage_project/migrations/0001_initial.py
netbox_manage_project/migrations/0002_remove_project_devices_remove_project_ipaddress_and_more.py
netbox_manage_project/migrations/0003_project_contact_project_user_count_and_more.py
netbox_manage_project/migrations/__init__.py
netbox_manage_project/models/__init__.py
netbox_manage_project/models/project.py
netbox_manage_project/models/quotatemplate.py
netbox_manage_project/templates/netbox_manage_project/project.html
netbox_manage_project/templates/netbox_manage_project/quotatemplate.html
netbox_manage_project/templates/netbox_manage_project/generic/bulk_remove.html
netbox_manage_project/templates/netbox_manage_project/inc/project_info.html
netbox_manage_project/templates/project_views/device.html
netbox_manage_project/templates/project_views/device_base.html
netbox_manage_project/templates/project_views/ipaddress.html
netbox_manage_project/templates/project_views/ipaddress_base.html
netbox_manage_project/templates/project_views/project_add_contact.html
netbox_manage_project/templates/project_views/project_add_devices.html
netbox_manage_project/templates/project_views/project_add_ipaddress.html
netbox_manage_project/templates/project_views/project_add_virtualmachine.html
netbox_manage_project/templates/project_views/project_user.html
netbox_manage_project/templates/project_views/project_user_base.html
netbox_manage_project/templates/project_views/project_user_remove.html
netbox_manage_project/templates/project_views/virtualmachine.html
netbox_manage_project/templates/project_views/virtualmachine_base.html
netbox_manage_project/views/__init__.py
netbox_manage_project-1.0.0.dist-info/METADATA
netbox_manage_project-1.0.0.dist-info/WHEEL
netbox_manage_project-1.0.0.dist-info/entry_points.txt
netbox_manage_project-1.0.0.dist-info/top_level.txt
netbox_manage_project-1.0.0.dist-info/RECORD
