Metadata-Version: 2.1
Name: netbox-manage-project
Version: 1.0.0
Summary: Netbox Plugin for Manage Project
Home-page: UNKNOWN
License: UNKNOWN
Platform: UNKNOWN
